Publish/__init__.py
Publish/gong.py
gongtestpub-1.0.8.dist-info/LICENSE
gongtestpub-1.0.8.dist-info/METADATA
gongtestpub-1.0.8.dist-info/WHEEL
gongtestpub-1.0.8.dist-info/top_level.txt
gongtestpub-1.0.8.dist-info/RECORD
