Metadata-Version: 2.1
Name: gongtestpub
Version: 1.0.8
Summary: <项目的简单描述>
Home-page: https://gitee.com/gongzhengyang
Author: gong
Author-email: 2976560783@qq.com
Maintainer: gong
Maintainer-email: 2976560783@qq.com
License: Apache License
Platform: all
